README
setup.py
django_postageapp/__init__.py
django_postageapp.egg-info/PKG-INFO
django_postageapp.egg-info/SOURCES.txt
django_postageapp.egg-info/dependency_links.txt
django_postageapp.egg-info/not-zip-safe
django_postageapp.egg-info/top_level.txt