Metadata-Version: 1.0
Name: django-postageapp
Version: 0.1.1a
Summary: Postageapp.com email backend for Django 1.2+
Home-page: http://github.com/vvarp/django-postageapp
Author: Maciek Szczesniak
Author-email: maciek@id43.net
License: UNKNOWN
Platform: UNKNOWN
Classifier: Development Status :: 4 - Beta
Classifier: Environment :: Web Environment
Classifier: Intended Audience :: Developers
Classifier: License :: OSI Approved
Classifier: Operating System :: OS Independent
Classifier: Framework :: Django
Classifier: Programming Language :: Python
